navigation/__init__.py
navigation/units.py
pynavigation-0.1.0b0.dist-info/LICENSE
pynavigation-0.1.0b0.dist-info/METADATA
pynavigation-0.1.0b0.dist-info/WHEEL
pynavigation-0.1.0b0.dist-info/top_level.txt
pynavigation-0.1.0b0.dist-info/RECORD
