Metadata-Version: 2.1
Name: pynavigation
Version: 0.1.0b0
Summary: A library that models units for navigation on Earth.
Home-page: https://github.com/ngfgrant/navigation
Author: Niall Grant
Author-email: ngfgrant@gmail.com
License: Apache2
Keywords: navigation,waypoint,position,route,latitude,longitude
Platform: UNKNOWN
Classifier: Development Status :: 3 - Alpha
Classifier: Environment :: Console
Classifier: Intended Audience :: Developers
Classifier: Natural Language :: English
Classifier: License :: OSI Approved :: Apache Software License
Classifier: Programming Language :: Python
Classifier: Programming Language :: Python :: 3
Classifier: Programming Language :: Python :: 3.4
Classifier: Programming Language :: Python :: 3.5
Classifier: Programming Language :: Python :: 3.6
Classifier: Programming Language :: Python :: 3.7
Classifier: Topic :: Software Development :: Libraries :: Python Modules
Requires-Python: >=3
